google_scholar_server.py
google_scholar_web_search.py
iflow_mcp_jackkuo666_mcp_server_google_scholar-0.1.0.dist-info/METADATA
iflow_mcp_jackkuo666_mcp_server_google_scholar-0.1.0.dist-info/WHEEL
iflow_mcp_jackkuo666_mcp_server_google_scholar-0.1.0.dist-info/entry_points.txt
iflow_mcp_jackkuo666_mcp_server_google_scholar-0.1.0.dist-info/RECORD
