Metadata-Version: 2.4
Name: iflow-mcp_jackkuo666_mcp-server-google-scholar
Version: 0.1.0
Summary: An MCP server for searching and retrieving articles from Google Scholar
Requires-Python: >=3.10
Requires-Dist: asyncio>=3.4.3
Requires-Dist: mcp[cli]>=1.4.1
Requires-Dist: scholarly>=1.7.0
